Metadata-Version: 1.0
Name: mock-useragent
Version: 2018.12.10.3
Summary: 类似fake-useragent，国内的网络导致用fake-useragent不太方便，所以诞生了mock-useragent这个项目
Home-page: https://github.com/find456789/mock-useragent
Author: find456789
Author-email: UNKNOWN
License: MIT
Keywords: useragent,mock-useragent,user agent
Platform: UNKNOWN
